dqx/__init__.py
dqx/analyzer.py
dqx/api.py
dqx/cache.py
dqx/common.py
dqx/compute.py
dqx/data.py
dqx/datasource.py
dqx/dialect.py
dqx/display.py
dqx/evaluator.py
dqx/functions.py
dqx/graph/__init__.py
dqx/graph/base.py
dqx/graph/nodes.py
dqx/graph/traversal.py
dqx/graph/visitors.py
dqx/models.py
dqx/ops.py
dqx/orm/__init__.py
dqx/orm/repositories.py
dqx/orm/session.py
dqx/plugins.py
dqx/profiles.py
dqx/provider.py
dqx/py.typed
dqx/specs.py
dqx/states.py
dqx/timer.py
dqx/utils.py
dqx/validator.py
dqlib-0.5.11.dist-info/WHEEL
dqlib-0.5.11.dist-info/entry_points.txt
dqlib-0.5.11.dist-info/METADATA
dqlib-0.5.11.dist-info/RECORD
