Metadata-Version: 2.3
Name: dqlib
Version: 0.5.11
Summary: Data Quality eXcellence
Author: Nam Pham
Author-email: Nam Pham <phamducnam@gmail.com>
Requires-Dist: duckdb>=1.3.2
Requires-Dist: msgpack>=1.1.1
Requires-Dist: pyarrow>=21.0.0
Requires-Dist: returns>=0.26.0
Requires-Dist: rich>=14.1.0
Requires-Dist: sqlalchemy>=2.0.43
Requires-Dist: sqlparse>=0.5.0
Requires-Dist: sympy>=1.14.0
Requires-Python: >=3.10, <=3.13
